{
    "builds": [
        {
            "aborted": true,
            "buildnum": 1,
            "graphid": "Czrlp3GBTue1yDGGkQrG4Q",
            "human_tasks": {
                "publish": false,
                "shipit": true,
                "signoff": false
            },
            "issues": [
                "kmoir: [Bug 1393639](https://bugzil.la/1393639) - tc indexes busted post-wv"
            ]
        },
        {
            "aborted": false,
            "buildnum": 2,
            "graphid": "D3aitJNqTUiJiQ5VnxHgvw",
            "human_tasks": {
                "publish": true,
                "shipit": true,
                "signoff": true
            },
            "issues": [
                "nthomas: [Bug 1393705](https://bugzil.la/1393705) - binary transpareny job no longer has netflow it needs, non blocking"
            ]
        }
    ],
    "date": "2017-08-24",
    "product": "devedition",
    "version": "56.0b6"
}