{
    "builds": [
        {
            "aborted": false,
            "buildnum": 1,
            "graphid": "XCFWUEmqSS6rcOfbyNj3Gw",
            "human_tasks": {
                "publish": true,
                "shipit": true,
                "signoff": true
            },
            "issues": [
                "nthomas: [Bug 1393705](https://bugzil.la/1393705) - binary transparency failed, disable for now"
            ]
        }
    ],
    "date": "2017-08-31",
    "product": "devedition",
    "version": "56.0b8"
}