{
    "builds": [
        {
            "aborted": false,
            "buildnum": 1,
            "graphid": "NFjEvc7YQ2uiBPPsJbOHWQ",
            "graphid_2": "dpGrIYPWQtGz-IbHs8foAA",
            "human_tasks": {
                "candidates": true,
                "publish": true,
                "pushapk": true,
                "shipit": true
            },
            "issues": [
                "SPECIAL REQUIREMENT: Talk to RelMan to see if it's the right time to [Bug 1397684](https://bugzilla.mozilla.org/show_bug.cgi?id=1397684) - [push-apk] 57 cycle: Turn off staged rollout on beta",
                "callek: Docs for fennec beta publish were wrongly pointing at BB docs on the wiki, found [old docs](https://github.com/mozilla/releasewarrior/commit/2550cf4cf33d86dd06c662025db3e79ed0378791#diff-763a878f526b6026bd5f5a3c37546f8bR317) with aki's help."
            ]
        }
    ],
    "date": "2017-10-10",
    "product": "fennec",
    "version": "57.0b7"
}