{
    "builds": [
        {
            "aborted": true,
            "buildnum": 1,
            "graphid": "j9-GjuTXQdiWOsiO6fL2Ag",
            "human_tasks": {
                "publish": false,
                "shipit": true,
                "signoff": false
            },
            "issues": [
                "nthomas: Forgot to land some funsize fixes on beta and hit issues with python deps"
            ]
        },
        {
            "aborted": true,
            "buildnum": 2,
            "graphid": "peh4qWmITmKjaT-Nwcan8A",
            "human_tasks": {
                "publish": false,
                "shipit": true,
                "signoff": false
            },
            "issues": [
                "asasaki: funsize-balrog issue https://github.com/mozilla-releng/releasetasks/pull/261"
            ]
        },
        {
            "aborted": true,
            "buildnum": 3,
            "graphid": "BoyrEYDOTWCZSOZ8u23YiA",
            "human_tasks": {
                "publish": false,
                "shipit": true,
                "signoff": false
            },
            "issues": [
                "mihaitabara: [Bug 1388312](https://bugzil.la/1388312) - 56.0b1 update tests fail: MAR_CHANNEL_MISMATCH_ERROR",
                "mihaitabara: [Bug 1388431](https://bugzil.la/1388431) - [win32/64, macosx64] Devedition: mars should be signed with Nightly key"
            ]
        },
        {
            "aborted": false,
            "buildnum": 4,
            "graphid": "LcsV9wwyTIOc_1U6_vgzDQ",
            "human_tasks": {
                "publish": false,
                "shipit": true,
                "signoff": false
            },
            "issues": []
        }
    ],
    "date": "2017-08-08",
    "product": "devedition",
    "version": "56.0b1"
}