{
    "builds": [
        {
            "aborted": false,
            "buildnum": 1,
            "graphid": "",
            "human_tasks": {
                "fxsignoff": false,
                "publish": false,
                "shipit": false
            },
            "issues": [
                "[Bug 1366916](https://bugzil.la/1366916) - version bumping failed after b9 due to alphabetical comparison"
            ]
        }
    ],
    "date": "2017-05-22",
    "product": "firefox",
    "version": "54.0b10"
}