{
    "builds": [
        {
            "aborted": true,
            "buildnum": 1,
            "graphid": "FFXri8qpQ-WEscEoLlMTcA",
            "human_tasks": {
                "publish": false,
                "shipit": true,
                "signoff": false
            },
            "issues": [
                "nthomas: 'Failed to start release promotion (graph ID: FFXri8qpQ-WEscEoLlMTcA). Error(s): You didn\\'t give the task-graph scopes allowing it define tasks on the queue.' in ship-it. Graph does exist in TC but all tasks are unscheduled. releaserunner log has 'You only have the scopes: ['docker-worker:*']'. Transient ?? Doing a build2 for deved l10n bustage anyway"
            ]
        },
        {
            "aborted": false,
            "buildnum": 2,
            "graphid": "dHzoExaZT1Gn8rymeKti7Q",
            "human_tasks": {
                "publish": false,
                "shipit": true,
                "signoff": false
            },
            "issues": [
                "nthomas: Bug 1391560 - Scope issue again so we backed out [b16f9e](https://github.com/mozilla-releng/releasetasks/commit/b16f9e02da4d41657d05b061928bb12da0f8d28a) from releasetasks. Bad graphs are [GjgfvPMfRcy02KAIUWua7w](https://tools.taskcluster.net/groups/GjgfvPMfRcy02KAIUWua7w) and [aWQ10bbMSIOrkZKissLfOA](https://tools.taskcluster.net/groups/aWQ10bbMSIOrkZKissLfOA)"
            ]
        }
    ],
    "date": "2017-08-18",
    "product": "firefox",
    "version": "56.0b4"
}
